epkeeperlib/__init__.py
epkeeperlib/bill/__init__.py
epkeeperlib/bill/ep_calc.py
epkeeperlib/bill/monitor_bill.py
epkeeperlib/bill/tariff.py
epkeeperlib/bill/tou.py
epkeeperlib/common/__init__.py
epkeeperlib/common/exceptions.py
epkeeperlib/common/utils.py
epkeeperlib/db/__init__.py
epkeeperlib/db/fetch_monitor.py
epkeeperlib/db/mysql_pool.py
epkeeperlib/db/sql_faraday.py
epkeeperlib/db/sql_oa.py
epkeeperlib/etc/__init__.py
epkeeperlib/etc/sql_faraday.py
epkeeperlib/etc/sql_oa.py
epkeeperlib/microgrid/__init__.py
epkeeperlib/microgrid/epk/__init__.py
epkeeperlib/microgrid/epk/input_meta.py
epkeeperlib/microgrid/epk/pvwatts_api.py
epkeeperlib/microgrid/nrel/__init__.py
epkeeperlib/microgrid/nrel/logger.py
epkeeperlib/microgrid/nrel/parse_api_responses_to_csv.py
epkeeperlib/microgrid/nrel/parse_api_responses_to_excel.py
epkeeperlib/microgrid/nrel/post_and_poll.py
epkeeperlib/microgrid/nrel/results_poller.py
epkeeperlib/nrel/__init__.py
epkeeperlib/nrel/logger.py
epkeeperlib/nrel/parse_api_responses_to_csv.py
epkeeperlib/nrel/parse_api_responses_to_excel.py
epkeeperlib/nrel/post_and_poll.py
epkeeperlib/nrel/results_poller.py
epkeeperlib-1.0.20.dist-info/LICENSE.txt
epkeeperlib-1.0.20.dist-info/METADATA
epkeeperlib-1.0.20.dist-info/WHEEL
epkeeperlib-1.0.20.dist-info/top_level.txt
epkeeperlib-1.0.20.dist-info/RECORD
